{
  "id": "aa041a8b-6b8d-4be0-aed4-4284d57221e8",
  "manufacturerCode": "rene-herse",
  "manufacturerProductCode": "fleecer-ridge-tc",
  "name": "Fleecer Ridge",
  "application": ["light-gravel", "rough-gravel", "singletrack"],
  "sizes": [
    {
      "name": "Standard",
      "bsd": 622,
      "width": 48,
      "treadColor": "black",
      "sidewallColor": "tan",
      "tpi": null,
      "weight": 545,
      "type": "tubeless"
    },
    {
      "name": "Extralight",
      "bsd": 622,
      "width": 48,
      "treadColor": "black",
      "sidewallColor": "tan",
      "tpi": null,
      "weight": 515,
      "type": "tubeless"
    },
    {
      "name": "Endurance",
      "bsd": 622,
      "width": 48,
      "treadColor": "black",
      "sidewallColor": "dark-tan",
      "tpi": null,
      "weight": 545,
      "type": "tubeless"
    },
  ]
}